README.md
setup.cfg
setup.py
pyruter/__init__.py
pyruter/api.py
pyruter/cli.py
pyruter/common.py
pyruter.egg-info/PKG-INFO
pyruter.egg-info/SOURCES.txt
pyruter.egg-info/dependency_links.txt
pyruter.egg-info/entry_points.txt
pyruter.egg-info/requires.txt
pyruter.egg-info/top_level.txt